MANIFEST.in
README
setup.py
app/__init__.py
app/runsever.py
app/raspberry_jam/__init__.py
app/raspberry_jam/filters.py
app/raspberry_jam/helpers.py
app/raspberry_jam/models.py
app/raspberry_jam/views.py
app/raspberry_jam/static/__init__.py
app/raspberry_jam/static/stream.js
app/raspberry_jam/templates/__init__.py
app/raspberry_jam/templates/root.html
app/raspberry_jam/templates/stream.html
app/spider/__init__.py
app/spider/crawl.py
raspberry_jam.egg-info/PKG-INFO
raspberry_jam.egg-info/SOURCES.txt
raspberry_jam.egg-info/dependency_links.txt
raspberry_jam.egg-info/top_level.txt