Metadata-Version: 1.0
Name: raspberry-jam
Version: 0.0.18
Summary: Raspberry Jam for music
Home-page: http://example.com
Author: Ralph Saunders
Author-email: ralph@ralphsaunders.co.uk
License: Private
Keywords: music
Platform: UNKNOWN
Classifier: Development Status :: 2 - Pre-Alpha
Classifier: Topic :: Utilities
Classifier: License :: Other/Proprietary License
